{
	"users": [
		{
			"id":1,
			"name":"Sviatoslav",
			"surname":"Kacmar",
			"job":"dog from money",
			"balance":"1500"
		},
		{
			"id": 2,
			"name": "Guzkodavilo",
			"surname": "Davlugusa",
			"balance": "-100$"
		},
		{
			"id": 3,
			"name": "N1 Z-patriot absolute",
			"surname": "samii krutoi",
			"balance": "-100$",
		}
	
	
	
	"products"
		{
			"id":11,
			"name":"Mukaltun",
			"price": "1$"
		},
		{
		        "id":12,
			"name":"Mukaltin",
			"price": "12$"
		},
		{
			"id": 21,			
			"name":"MukaltinDanya",
			"price": "250000$"
		}
	]


		




	

	

		

=======
	]	
}
>>>>>>> cbbbce96b11a2802a9c25e284cd2f949ea22bdff
